cumm_cu113-0.5.3.dist-info/top_level.txt
cumm_cu113-0.5.3.dist-info/METADATA
cumm_cu113-0.5.3.dist-info/RECORD
cumm_cu113-0.5.3.dist-info/WHEEL
cumm_cu113-0.5.3.dist-info/LICENSE
cumm_cu113.libs/libcudart-a7b20f20.so.11.3.109
cumm_cu113.libs/libnvrtc-builtins-4730a239.so.11.3.109
cumm_cu113.libs/libnvrtc-1ea278b5.so.11.3.109
cumm/tensorview_bind_anno.pyi
cumm/dtypes.py
cumm/perftools.py
cumm/tensorview_bind.py
cumm/common.py
cumm/core_cc.cpython-311-x86_64-linux-gnu.so
cumm/inliner.py
cumm/constants.py
cumm/__init__.py
cumm/__version__.py
cumm/conv/main.py
cumm/conv/kernel.py
cumm/conv/main_real.py
cumm/conv/bases.py
cumm/conv/main_real_spconv.py
cumm/conv/sparse_iters.py
cumm/conv/algo.py
cumm/conv/input_iters.py
cumm/conv/params.py
cumm/conv/__init__.py
cumm/conv/nvrtc_code.py
cumm/conv/algospec/all.py
cumm/conv/algospec/volta.py
cumm/conv/algospec/core.py
cumm/conv/algospec/turing.py
cumm/conv/algospec/simt.py
cumm/conv/algospec/__init__.py
cumm/develop/__init__.py
cumm/develop/eigendev.py
cumm/develop/mathgen.py
cumm/cudasim/debug.py
cumm/cudasim/checkers.py
cumm/cudasim/__init__.py
cumm/gemmv2/__init__.py
cumm/devapps/template.py
cumm/devapps/__init__.py
cumm/gemm/turing_out_iters.py
cumm/gemm/main.py
cumm/gemm/out_iters.py
cumm/gemm/kernel.py
cumm/gemm/turing_my_iters.py
cumm/gemm/codeops.py
cumm/gemm/main_real.py
cumm/gemm/cutlasstest.py
cumm/gemm/mask.py
cumm/gemm/utils.py
cumm/gemm/layout.py
cumm/gemm/bases.py
cumm/gemm/thread_map.py
cumm/gemm/main_profile.py
cumm/gemm/main_simu.py
cumm/gemm/volta_iters.py
cumm/gemm/output.py
cumm/gemm/constants.py
cumm/gemm/layout_tensorop.py
cumm/gemm/gather.py
cumm/gemm/turing_iters.py
cumm/gemm/volta_out_iters.py
cumm/gemm/mask_iters.py
cumm/gemm/__init__.py
cumm/gemm/main_real_test.py
cumm/gemm/nvrtc_code.py
cumm/gemm/dev_gemm.py
cumm/gemm/wmma/volta.py
cumm/gemm/wmma/turing.py
cumm/gemm/wmma/simt.py
cumm/gemm/wmma/__init__.py
cumm/gemm/core/metaarray.py
cumm/gemm/core/__init__.py
cumm/gemm/output_op/linear.py
cumm/gemm/output_op/__init__.py
cumm/gemm/output_op/apply.py
cumm/gemm/outputs/__init__.py
