Metadata-Version: 2.1
Name: cumm-cu113
Version: 0.5.3
Summary: CUda Matrix Multiply library
Home-page: https://github.com/FindDefinition/cumm
Author: Yan Yan
Author-email: yanyan.sub@outlook.com
License: MIT
Classifier: License :: OSI Approved :: MIT License
Classifier: Programming Language :: Python
Classifier: Programming Language :: Python :: 3
Classifier: Programming Language :: Python :: Implementation :: CPython
Classifier: Programming Language :: Python :: Implementation :: PyPy
Requires-Python: >=3.6
License-File: LICENSE
Requires-Dist: pccm >=0.4.2
Requires-Dist: pybind11 >=2.6.0
Requires-Dist: fire
Requires-Dist: numpy
Requires-Dist: contextvars ; python_version == "3.6"
